Products.MegamanicEditContentTypes-configure.zcml
setup.py
Products/__init__.py
Products.MegamanicEditContentTypes.egg-info/PKG-INFO
Products.MegamanicEditContentTypes.egg-info/SOURCES.txt
Products.MegamanicEditContentTypes.egg-info/dependency_links.txt
Products.MegamanicEditContentTypes.egg-info/entry_points.txt
Products.MegamanicEditContentTypes.egg-info/namespace_packages.txt
Products.MegamanicEditContentTypes.egg-info/not-zip-safe
Products.MegamanicEditContentTypes.egg-info/requires.txt
Products.MegamanicEditContentTypes.egg-info/top_level.txt
Products/MegamanicEditContentTypes/__init__.py
Products/MegamanicEditContentTypes/changes.txt
Products/MegamanicEditContentTypes/config.py
Products/MegamanicEditContentTypes/configure.zcml
Products/MegamanicEditContentTypes/interfaces.py
Products/MegamanicEditContentTypes/readme.txt
Products/MegamanicEditContentTypes/zope2.py
Products/MegamanicEditContentTypes/content/__init__.py
Products/MegamanicEditContentTypes/content/address.py
Products/MegamanicEditContentTypes/content/attendeeevent.py
Products/MegamanicEditContentTypes/content/configure.zcml
Products/MegamanicEditContentTypes/content/contact.py
Products/MegamanicEditContentTypes/content/contactlandingpage.py
Products/MegamanicEditContentTypes/content/emailaddress.py
Products/MegamanicEditContentTypes/content/emailmessage.py
Products/MegamanicEditContentTypes/content/netaddress.py
Products/MegamanicEditContentTypes/content/phonenumber.py
Products/MegamanicEditContentTypes/content/workplaceandworktitle.py
Products/MegamanicEditContentTypes/profiles/default/factorytool.xml
Products/MegamanicEditContentTypes/profiles/default/metadata.xml
Products/MegamanicEditContentTypes/profiles/default/skins.xml
Products/MegamanicEditContentTypes/profiles/default/types.xml
Products/MegamanicEditContentTypes/profiles/default/types/Address.xml
Products/MegamanicEditContentTypes/profiles/default/types/Attendee_event.xml
Products/MegamanicEditContentTypes/profiles/default/types/Contact.xml
Products/MegamanicEditContentTypes/profiles/default/types/Contact_landing_page.xml
Products/MegamanicEditContentTypes/profiles/default/types/Email_address.xml
Products/MegamanicEditContentTypes/profiles/default/types/Email_message.xml
Products/MegamanicEditContentTypes/profiles/default/types/Net_address.xml
Products/MegamanicEditContentTypes/profiles/default/types/Phone_number.xml
Products/MegamanicEditContentTypes/profiles/default/types/Workplace_and_work_title.xml
